MANIFEST.in
README.rst
setup.py
autoblocks/__init__.py
autoblocks/admin.py
autoblocks/models.py
autoblocks/tests.py
autoblocks.egg-info/PKG-INFO
autoblocks.egg-info/SOURCES.txt
autoblocks.egg-info/dependency_links.txt
autoblocks.egg-info/requires.txt
autoblocks.egg-info/top_level.txt
autoblocks/templatetags/__init__.py
autoblocks/templatetags/autoblocks_tags.py
autoblocks/templatetags/helpers.py