Metadata-Version: 1.0
Name: autoblocks
Version: 1.0.4
Summary: Place arbitrary django-cms placeholders into templates
Home-page: https://github.com/Strathcom/django-cms-autoblocks
Author: Luke Hutscal
Author-email: support@strathcom.com
License: BSD License
Platform: OS Independent
